js.adminlte-2.4.9-py3.7-nspkg.pth
js/adminlte/__init__.py
js/adminlte/test_adminlte.txt
js/adminlte/resources/all.js
js/adminlte/resources/css/adminlte.css
js/adminlte/resources/css/adminlte.css.map
js/adminlte/resources/css/adminlte.min.css
js/adminlte/resources/css/adminlte.min.css.map
js/adminlte/resources/css/skin-blue-light.css
js/adminlte/resources/css/skin-blue-light.min.css
js/adminlte/resources/css/skin-blue.css
js/adminlte/resources/css/skin-blue.min.css
js/adminlte/resources/img/avatar.png
js/adminlte/resources/img/avatar04.png
js/adminlte/resources/img/avatar2.png
js/adminlte/resources/img/avatar3.png
js/adminlte/resources/img/avatar5.png
js/adminlte/resources/img/default-50x50.gif
js/adminlte/resources/img/icons.png
js/adminlte/resources/img/credit/american-express.png
js/adminlte/resources/img/credit/cirrus.png
js/adminlte/resources/img/credit/mastercard.png
js/adminlte/resources/img/credit/mestro.png
js/adminlte/resources/img/credit/paypal.png
js/adminlte/resources/img/credit/paypal2.png
js/adminlte/resources/img/credit/visa.png
js/adminlte/resources/js/adminlte.js
js/adminlte/resources/js/adminlte.min.js
js/adminlte/resources/plugins/bootstrap-datepicker/bootstrap-datepicker.css
js/adminlte/resources/plugins/bootstrap-datepicker/bootstrap-datepicker.css.map
js/adminlte/resources/plugins/bootstrap-datepicker/bootstrap-datepicker.js
js/adminlte/resources/plugins/bootstrap-datepicker/bootstrap-datepicker.min.css
js/adminlte/resources/plugins/bootstrap-datepicker/bootstrap-datepicker.min.js
js/adminlte/resources/plugins/bootstrap-timepicker/bootstrap-timepicker.css
js/adminlte/resources/plugins/bootstrap-timepicker/bootstrap-timepicker.js
js/adminlte/resources/plugins/bootstrap-timepicker/bootstrap-timepicker.min.css
js/adminlte/resources/plugins/bootstrap-timepicker/bootstrap-timepicker.min.js
js/adminlte/resources/plugins/bootstrap-wysihtml5/bootstrap3-wysihtml5.css
js/adminlte/resources/plugins/bootstrap-wysihtml5/bootstrap3-wysihtml5.js
js.adminlte-2.4.9.dist-info/LICENSE.txt
js.adminlte-2.4.9.dist-info/METADATA
js.adminlte-2.4.9.dist-info/WHEEL
js.adminlte-2.4.9.dist-info/entry_points.txt
js.adminlte-2.4.9.dist-info/namespace_packages.txt
js.adminlte-2.4.9.dist-info/top_level.txt
js.adminlte-2.4.9.dist-info/RECORD
