Metadata-Version: 2.1
Name: js.adminlte
Version: 2.4.9
Summary: Fanstatic packaging of AdminLTE
Home-page: https://github.com/ephraimbuddy/js.adminlte
Author: Ephraim Anierobi
Author-email: ephraimanierobi@gmail.com
License: BSD
Keywords: fanstatic AdminLTE dashboard templates Ephraim Anierobi
Platform: UNKNOWN
Requires-Dist: fanstatic
Requires-Dist: js.bootstrap
Requires-Dist: setuptools
